libreria_selenium_pers/__init__.py
libreria_selenium_pers/config.py
libreria_selenium_pers/drivers.py
libreria_selenium_pers/selenium_tools.py
libreria_selenium_pers/telegram_tools.py
libreria_selenium_pers/tools.py
libreria_selenium_pers-0.4.dist-info/METADATA
libreria_selenium_pers-0.4.dist-info/WHEEL
libreria_selenium_pers-0.4.dist-info/top_level.txt
libreria_selenium_pers-0.4.dist-info/RECORD
